{"SRV03": {"IDs Pacientes": ["1", "26722"], "IDs Procedimentos": [{"idProcedimento": "10", "idPaciente": "1"}, {"idProcedimento": "2", "idPaciente": "1"}, {"idProcedimento": "222", "idPaciente": "1"}], "IDs Medicos": ["14123-MG", "18864-MA", "42820-RJ", "10497-MS", "80656-MG", "27645-RJ", "63339-MS", "98236-MG", "87529-AM", "25377-RN", "34543-AC", "98750-MG", "33742-RJ", "63292-GO", "49099-AM", "80689-SP"]}, "SRV01": {"IDs Pacientes": ["68213", "91836", "6", "36699", "7"], "IDs Procedimentos": [{"idProcedimento": "7", "idPaciente": "6"}, {"idProcedimento": "1", "idPaciente": "6"}, {"idProcedimento": "666", "idPaciente": "7"}, {"idProcedimento": "9", "idPaciente": "6"}, {"idProcedimento": "8", "idPaciente": "7"}], "IDs Medicos": ["10678-SP", "97815-MA", "83192-GO", "56451-AM", "45876-AC", "25154-SP", "98691-BA", "37628-GO", "13653-GO", "32145-MG"]}}